<?xml version="1.0" encoding="utf-8" ?>
<dwsync>
<file name="dialog.css" server="www.ili-studios.com//domains/erp.ili-studios.com/public_html/" local="130909279828659002" remote="130919019000000000" Dst="0" />
<file name="dialog_ie.css" server="www.ili-studios.com//domains/erp.ili-studios.com/public_html/" local="130909279828719064" remote="130919019000000000" Dst="0" />
<file name="dialog_ie8.css" server="www.ili-studios.com//domains/erp.ili-studios.com/public_html/" local="130909279828829163" remote="130919019000000000" Dst="0" />
<file name="dialog_ie7.css" server="www.ili-studios.com//domains/erp.ili-studios.com/public_html/" local="130909279828769113" remote="130919019000000000" Dst="0" />
<file name="dialog_iequirks.css" server="www.ili-studios.com//domains/erp.ili-studios.com/public_html/" local="130909279828869199" remote="130919019000000000" Dst="0" />
<file name="dialog_opera.css" server="www.ili-studios.com//domains/erp.ili-studios.com/public_html/" local="130909279828939296" remote="130919019000000000" Dst="0" />
<file name="editor.css" server="www.ili-studios.com//domains/erp.ili-studios.com/public_html/" local="130909279828989298" remote="130919019000000000" Dst="0" />
<file name="editor_gecko.css" server="www.ili-studios.com//domains/erp.ili-studios.com/public_html/" local="130909279829049374" remote="130919019000000000" Dst="0" />
<file name="icons.png" server="www.ili-studios.com//domains/erp.ili-studios.com/public_html/" local="130909279829269559" remote="130919019000000000" Dst="0" />
<file name="editor_ie8.css" server="www.ili-studios.com//domains/erp.ili-studios.com/public_html/" local="130909279829199492" remote="130919019000000000" Dst="0" />
<file name="editor_ie.css" server="www.ili-studios.com//domains/erp.ili-studios.com/public_html/" local="130909279829109411" remote="130919019000000000" Dst="0" />
<file name="editor_ie7.css" server="www.ili-studios.com//domains/erp.ili-studios.com/public_html/" local="130909279829149477" remote="130919019000000000" Dst="0" />
<file name="editor_iequirks.css" server="www.ili-studios.com//domains/erp.ili-studios.com/public_html/" local="130909279829259558" remote="130919019000000000" Dst="0" />
<file name="readme.md" server="www.ili-studios.com//domains/erp.ili-studios.com/public_html/" local="130909279829349631" remote="130919019000000000" Dst="0" />
</dwsync>